Metadata-Version: 1.1
Name: python-git-package
Version: 0.3.3
Summary: A scaffolding tool for python packages
Home-page: https://github.com/BrechtBa/python-git-package
Author: Brecht Baeten
Author-email: brecht.baeten@gmail.com
License: GPLv3
Platform: UNKNOWN
Classifier: Programming Language :: Python :: 2.7
